pyvklogin/__init__.py
pyvklogin/pyvklogin.py
pyvklogin/pyvklogin_ext.py
pyvklogin-0.1.3.dist-info/LICENSE.txt
pyvklogin-0.1.3.dist-info/METADATA
pyvklogin-0.1.3.dist-info/WHEEL
pyvklogin-0.1.3.dist-info/top_level.txt
pyvklogin-0.1.3.dist-info/RECORD
